NetRecorder/NetTraRec.py
NetRecorder/NetTraRecServer.py
NetRecorder/__init__.py
NetRecorder/common_scheduler.py
NetRecorder/gear_for_nr.py
NetRecorder/nettrarec.raw
NetRecorder/math_works/Cosine_Similarity.py
NetRecorder/math_works/Euclidean_Distance.py
NetRecorder/math_works/Frechet_Distance.py
NetRecorder/math_works/Pearson_CorrelationCoefficient.py
NetRecorder/math_works/__init__.py
NetRecorder/some_gears/__init__.py
NetRecorder/some_gears/get_ip_location.py
NetRecorder/some_gears/secure_ssh_filter.py
NetTraRec-0.1.12.dist-info/LICENSE
NetTraRec-0.1.12.dist-info/METADATA
NetTraRec-0.1.12.dist-info/WHEEL
NetTraRec-0.1.12.dist-info/entry_points.txt
NetTraRec-0.1.12.dist-info/top_level.txt
NetTraRec-0.1.12.dist-info/RECORD
