Metadata-Version: 2.1
Name: NetTraRec
Version: 0.1.12
Summary: 服务器流量监控小工具
Home-page: https://github.com/ga1008/net_tracfic_recorder
Author: Guardian
Author-email: zhling2012@live.com
Maintainer: Guardian
Maintainer-email: zhling2012@live.com
License: UNKNOWN
Platform: UNKNOWN
Classifier: Programming Language :: Python :: 3
Classifier: License :: OSI Approved :: MIT License
Classifier: Operating System :: OS Independent
Requires-Dist: basecolors
Requires-Dist: psutil
Requires-Dist: redis
Requires-Dist: requests
Requires-Dist: numpy
Requires-Dist: scipy
